habana_frameworks/tensorflow/py_synapse_logger.py
habana_frameworks/tensorflow/library_loader.py
habana_frameworks/tensorflow/lib_utils.py
habana_frameworks/tensorflow/multinode_helpers.py
habana_frameworks/tensorflow/habana_device.py
habana_frameworks/tensorflow/sysconfig.py
habana_frameworks/tensorflow/backward_compatibility.py
habana_frameworks/tensorflow/habana_estimator.py
habana_frameworks/tensorflow/__init__.py
habana_frameworks/tensorflow/patching.py
habana_frameworks/tensorflow/allcompare.py
habana_frameworks/tensorflow/synapse_logger_helpers.py
habana_frameworks/tensorflow/util.py
habana_frameworks/tensorflow/hccl.py
habana_frameworks/tensorflow/impl_override_utils.py
habana_frameworks/tensorflow/ops/instance_norm.py
habana_frameworks/tensorflow/ops/layer_norm.py
habana_frameworks/tensorflow/ops/gelu.py
habana_frameworks/tensorflow/optimizers/yogi.py
habana_frameworks/tensorflow/optimizers/cocob.py
habana_frameworks/tensorflow/optimizers/novograd.py
habana_frameworks/tensorflow/optimizers/radam.py
habana_frameworks/tensorflow/optimizers/lazy_adam.py
habana_frameworks/tensorflow/optimizers/__init__.py
habana_frameworks/tensorflow/optimizers/conditional_gradient.py
habana_frameworks/tensorflow/optimizers/lamb.py
habana_frameworks/tensorflow/optimizers/cyclical_learning_rate.py
habana_frameworks/tensorflow/optimizers/lookahead.py
habana_frameworks/tensorflow/distribute/_hpu_strategy.py
habana_frameworks/tensorflow/distribute/__init__.py
habana_frameworks/tensorflow/profiling/hook_init.py
habana_frameworks/tensorflow/internal/version_getter.py
habana_frameworks/tensorflow/internal/__init__.py
habana_frameworks/tensorflow/internal/allcompare.py
habana_frameworks/tensorflow/internal/hccl.py
habana_frameworks/tensorflow/tf2_15_0/include/habanalabs/hpu_kernel_context.h
habana_frameworks/tensorflow/tf2_15_0/include/habanalabs/hccl_integration.h
habana_frameworks/tensorflow/tf2_15_0/include/habanalabs/hpu_kernel.h
habana_tensorflow-1.14.0.493.dist-info/WHEEL
habana_tensorflow-1.14.0.493.dist-info/LICENSE.txt
habana_tensorflow-1.14.0.493.dist-info/top_level.txt
habana_tensorflow-1.14.0.493.dist-info/RECORD
habana_tensorflow-1.14.0.493.dist-info/METADATA
habana_tensorflow-1.14.0.493.dist-info/third-party-programs.txt
