Metadata-Version: 2.1
Name: habana-tensorflow
Version: 1.14.0.493
Summary: This package contains Habana® TensorFlow bridge that allows to work with Habana® Gaudi®
Home-page: https://habana.ai/
Author: Habana Labs, Ltd. an Intel Company
Author-email: support@habana.ai
License: See LICENSE.txt and third-party-programs.txt
Classifier: Development Status :: 5 - Production/Stable
Classifier: Intended Audience :: Developers
Classifier: Intended Audience :: Science/Research
Classifier: License :: Other/Proprietary License
Classifier: Operating System :: Unix
Classifier: Programming Language :: Python :: 3
Classifier: Programming Language :: Python :: 3.8
Classifier: Programming Language :: Python :: 3.10
Classifier: Programming Language :: Python :: 3 :: Only
Classifier: Topic :: Scientific/Engineering
Classifier: Topic :: Scientific/Engineering :: Mathematics
Classifier: Topic :: Scientific/Engineering :: Artificial Intelligence
Classifier: Topic :: Software Development
Classifier: Topic :: Software Development :: Libraries
Classifier: Topic :: Software Development :: Libraries :: Python Modules
License-File: ../LICENSE.txt
License-File: ../third-party-programs.txt
Requires-Dist: packaging
Provides-Extra: media
Requires-Dist: habana-media-loader ; extra == 'media'
